imgrep/__init__.py
imgrep/main.py
imgrep-0.0.4.dist-info/LICENSE
imgrep-0.0.4.dist-info/METADATA
imgrep-0.0.4.dist-info/WHEEL
imgrep-0.0.4.dist-info/entry_points.txt
imgrep-0.0.4.dist-info/top_level.txt
imgrep-0.0.4.dist-info/RECORD
