Metadata-Version: 2.1
Name: imgrep
Version: 0.0.4
Summary: Grep for text in images
Author-email: Fynn Freyer <fynn@fynns.site>
Project-URL: Homepage, https://github.com/FynnFreyer/imgrep
Project-URL: Bug Tracker, https://github.com/FynnFreyer/imgrep/issues
Classifier: Development Status :: 3 - Alpha
Classifier: Programming Language :: Python :: 3
Classifier: License :: OSI Approved :: MIT License
Classifier: Operating System :: OS Independent
Requires-Python: >=3.7
License-File: LICENSE
Requires-Dist: Pillow
Requires-Dist: pytesseract
